LICENSE
MANIFEST.in
README.rst
requirements.txt
setup.py
lib/pynml/__init__.py
lib/pynml/exceptions.py
lib/pynml/manager.py
lib/pynml/nml.py
lib/pynml/spec.py
lib/pynml.egg-info/PKG-INFO
lib/pynml.egg-info/SOURCES.txt
lib/pynml.egg-info/dependency_links.txt
lib/pynml.egg-info/requires.txt
lib/pynml.egg-info/top_level.txt