Metadata-Version: 1.1
Name: pynml
Version: 1.1.1
Summary: Python library for the Network Markup Language (NML) standard for network topologies representation.
Home-page: http://pynml.rtfd.org/
Author: Hewlett Packard Enterprise Development LP
Author-email: hpe-networking@lists.hp.com
License: UNKNOWN
Keywords: pynml
Platform: UNKNOWN
Classifier: Development Status :: 3 - Alpha
Classifier: Intended Audience :: Developers
Classifier: License :: OSI Approved :: Apache Software License
Classifier: Natural Language :: English
Classifier: Operating System :: POSIX :: Linux
Classifier: Programming Language :: Python :: 2
Classifier: Programming Language :: Python :: 2.7
Classifier: Programming Language :: Python :: 3
Classifier: Programming Language :: Python :: 3.4
